shirin/__init__.py
shirin/_util_codes.py
shirin-0.0.5.dist-info/LICENSE
shirin-0.0.5.dist-info/METADATA
shirin-0.0.5.dist-info/WHEEL
shirin-0.0.5.dist-info/top_level.txt
shirin-0.0.5.dist-info/RECORD
